read-only-attributes/__init__.py
read-only-attributes/read-only-attributes.py
roa/__init__.py
roa/read_only_attributes.py
read_only_attributes-1.2.dist-info/LICENSE
read_only_attributes-1.2.dist-info/METADATA
read_only_attributes-1.2.dist-info/WHEEL
read_only_attributes-1.2.dist-info/top_level.txt
read_only_attributes-1.2.dist-info/RECORD
