Metadata-Version: 2.1
Name: read-only-attributes
Version: 1.2
Summary: Makes read only attributes for a Python class
Home-page: https://github.com/tek-shinobi/read-only-attributes
Author: tek.shinobi
Author-email: tek.shinobi.ninja@gmail.com
License: MIT
Keywords: read,only,attributes,property
Platform: any
Classifier: Development Status :: 5 - Production/Stable
Classifier: Intended Audience :: Developers
Classifier: Topic :: Software Development :: Libraries :: Python Modules
Classifier: License :: OSI Approved :: MIT License
Classifier: Programming Language :: Python :: 3
Classifier: Programming Language :: Python :: 3.6
Classifier: Programming Language :: Python :: 3.7
Classifier: Programming Language :: Python :: 3.8
Classifier: Operating System :: OS Independent
